agentic_learning/__init__.py
agentic_learning/core.py
agentic_learning/types.py
agentic_learning/client/__init__.py
agentic_learning/client/utils.py
agentic_learning/client/agents/__init__.py
agentic_learning/client/agents/client.py
agentic_learning/client/agents/sleeptime.py
agentic_learning/client/memory/__init__.py
agentic_learning/client/memory/client.py
agentic_learning/client/memory/context.py
agentic_learning/client/messages/__init__.py
agentic_learning/client/messages/client.py
agentic_learning/client/messages/context.py
agentic_learning/interceptors/__init__.py
agentic_learning/interceptors/anthropic.py
agentic_learning/interceptors/base.py
agentic_learning/interceptors/claude.py
agentic_learning/interceptors/gemini.py
agentic_learning/interceptors/openai.py
agentic_learning/interceptors/registry.py
agentic_learning/interceptors/utils.py
agentic_learning-0.4.2.dist-info/METADATA
agentic_learning-0.4.2.dist-info/WHEEL
agentic_learning-0.4.2.dist-info/RECORD
