Metadata-Version: 2.4
Name: agentic-learning
Version: 0.4.2
Summary: Drop-in SDK to add an AI memory layer to any application. Works with OpenAI, Anthropic, Gemini, Claude.
Project-URL: Homepage, https://github.com/letta-ai/agentic-learning-sdk
Project-URL: Repository, https://github.com/letta-ai/agentic-learning-sdk
Project-URL: Issues, https://github.com/letta-ai/agentic-learning-sdk/issues
Project-URL: Documentation, https://github.com/letta-ai/agentic-learning-sdk#readme
Project-URL: Source Code, https://github.com/letta-ai/agentic-learning-sdk
Author-email: Caren Thomas <caren@letta.com>
License: Apache-2.0
Keywords: agent-memory,ai-agents,ai-memory,anthropic,claude,context-management,continual-learning,conversational-ai,gemini,letta,llm,llm-memory,memory-layer,openai,persistent-memory,rag,semantic-memory,stateful-agents
Classifier: Development Status :: 4 - Beta
Classifier: Intended Audience :: Developers
Classifier: License :: OSI Approved :: Apache Software License
Classifier: Programming Language :: Python :: 3
Classifier: Programming Language :: Python :: 3.10
Classifier: Programming Language :: Python :: 3.11
Classifier: Programming Language :: Python :: 3.12
Classifier: Topic :: Scientific/Engineering :: Artificial Intelligence
Classifier: Topic :: Software Development :: Libraries :: Python Modules
Requires-Python: >=3.10
Requires-Dist: httpx-sse>=0.4.0
Requires-Dist: httpx>=0.21.2
Requires-Dist: letta-client==1.0.0a20
Requires-Dist: pydantic-core>=2.18.2
Requires-Dist: pydantic>=1.9.2
Requires-Dist: typing-extensions>=4.0.0
Provides-Extra: all
Requires-Dist: anthropic>=0.64.0; extra == 'all'
Requires-Dist: google-generativeai>=0.8.0; extra == 'all'
Requires-Dist: openai>=1.102.0; extra == 'all'
Provides-Extra: anthropic
Requires-Dist: anthropic>=0.64.0; extra == 'anthropic'
Provides-Extra: claude
Requires-Dist: claude-agent-sdk>=0.1.0; extra == 'claude'
Provides-Extra: dev
Requires-Dist: pytest-asyncio>=0.21.0; extra == 'dev'
Requires-Dist: pytest>=7.0.0; extra == 'dev'
Provides-Extra: gemini
Requires-Dist: google-generativeai>=0.8.0; extra == 'gemini'
Provides-Extra: openai
Requires-Dist: openai>=1.102.0; extra == 'openai'
